{
  "id": "a4040ca3-49e7-4356-b864-dcb227828209",
  "prevId": "00000000-0000-0000-0000-000000000000",
  "version": "7",
  "dialect": "postgresql",
  "tables": {
    "public.users": {
      "name": "users",
      "schema": "",
      "columns": {
        "id": {
          "name": "id",
          "type": "uuid",
          "primaryKey": true,
          "notNull": true,
          "default": "gen_random_uuid()"
        },
        "email": {
          "name": "email",
          "type": "varchar(255)",
          "primaryKey": false,
          "notNull": true
        },
        "name": {
          "name": "name",
          "type": "varchar(255)",
          "primaryKey": false,
          "notNull": true
        },
        "password_hash": {
          "name": "password_hash",
          "type": "varchar(255)",
          "primaryKey": false,
          "notNull": true
        },
        "npm_token_encrypted": {
          "name": "npm_token_encrypted",
          "type": "text",
          "primaryKey": false,
          "notNull": false
        },
        "plan": {
          "name": "plan",
          "type": "plan",
          "typeSchema": "public",
          "primaryKey": false,
          "notNull": true,
          "default": "'free'"
        },
        "created_at": {
          "name": "created_at",
          "type": "timestamp with time zone",
          "primaryKey": false,
          "notNull": true,
          "default": "now()"
        },
        "updated_at": {
          "name": "updated_at",
          "type": "timestamp with time zone",
          "primaryKey": false,
          "notNull": true,
          "default": "now()"
        }
      },
      "indexes": {},
      "foreignKeys": {},
      "compositePrimaryKeys": {},
      "uniqueConstraints": {
        "users_email_unique": {
          "name": "users_email_unique",
          "nullsNotDistinct": false,
          "columns": [
            "email"
          ]
        }
      },
      "policies": {},
      "checkConstraints": {},
      "isRLSEnabled": false
    },
    "public.refresh_tokens": {
      "name": "refresh_tokens",
      "schema": "",
      "columns": {
        "id": {
          "name": "id",
          "type": "uuid",
          "primaryKey": true,
          "notNull": true,
          "default": "gen_random_uuid()"
        },
        "user_id": {
          "name": "user_id",
          "type": "uuid",
          "primaryKey": false,
          "notNull": true
        },
        "token_hash": {
          "name": "token_hash",
          "type": "varchar(255)",
          "primaryKey": false,
          "notNull": true
        },
        "expires_at": {
          "name": "expires_at",
          "type": "timestamp with time zone",
          "primaryKey": false,
          "notNull": true
        },
        "created_at": {
          "name": "created_at",
          "type": "timestamp with time zone",
          "primaryKey": false,
          "notNull": true,
          "default": "now()"
        }
      },
      "indexes": {},
      "foreignKeys": {
        "refresh_tokens_user_id_users_id_fk": {
          "name": "refresh_tokens_user_id_users_id_fk",
          "tableFrom": "refresh_tokens",
          "tableTo": "users",
          "columnsFrom": [
            "user_id"
          ],
          "columnsTo": [
            "id"
          ],
          "onDelete": "cascade",
          "onUpdate": "no action"
        }
      },
      "compositePrimaryKeys": {},
      "uniqueConstraints": {},
      "policies": {},
      "checkConstraints": {},
      "isRLSEnabled": false
    },
    "public.projects": {
      "name": "projects",
      "schema": "",
      "columns": {
        "id": {
          "name": "id",
          "type": "uuid",
          "primaryKey": true,
          "notNull": true,
          "default": "gen_random_uuid()"
        },
        "user_id": {
          "name": "user_id",
          "type": "uuid",
          "primaryKey": false,
          "notNull": true
        },
        "name": {
          "name": "name",
          "type": "varchar(255)",
          "primaryKey": false,
          "notNull": true
        },
        "slug": {
          "name": "slug",
          "type": "varchar(255)",
          "primaryKey": false,
          "notNull": true
        },
        "package_name": {
          "name": "package_name",
          "type": "varchar(255)",
          "primaryKey": false,
          "notNull": true
        },
        "description": {
          "name": "description",
          "type": "text",
          "primaryKey": false,
          "notNull": false
        },
        "frameworks": {
          "name": "frameworks",
          "type": "jsonb",
          "primaryKey": false,
          "notNull": true,
          "default": "'[\"react\"]'::jsonb"
        },
        "latest_version": {
          "name": "latest_version",
          "type": "varchar(50)",
          "primaryKey": false,
          "notNull": false
        },
        "status": {
          "name": "status",
          "type": "project_status",
          "typeSchema": "public",
          "primaryKey": false,
          "notNull": true,
          "default": "'active'"
        },
        "created_at": {
          "name": "created_at",
          "type": "timestamp with time zone",
          "primaryKey": false,
          "notNull": true,
          "default": "now()"
        },
        "updated_at": {
          "name": "updated_at",
          "type": "timestamp with time zone",
          "primaryKey": false,
          "notNull": true,
          "default": "now()"
        }
      },
      "indexes": {},
      "foreignKeys": {
        "projects_user_id_users_id_fk": {
          "name": "projects_user_id_users_id_fk",
          "tableFrom": "projects",
          "tableTo": "users",
          "columnsFrom": [
            "user_id"
          ],
          "columnsTo": [
            "id"
          ],
          "onDelete": "cascade",
          "onUpdate": "no action"
        }
      },
      "compositePrimaryKeys": {},
      "uniqueConstraints": {
        "projects_user_id_package_name_unique": {
          "name": "projects_user_id_package_name_unique",
          "nullsNotDistinct": false,
          "columns": [
            "user_id",
            "package_name"
          ]
        }
      },
      "policies": {},
      "checkConstraints": {},
      "isRLSEnabled": false
    },
    "public.icons": {
      "name": "icons",
      "schema": "",
      "columns": {
        "id": {
          "name": "id",
          "type": "uuid",
          "primaryKey": true,
          "notNull": true,
          "default": "gen_random_uuid()"
        },
        "project_id": {
          "name": "project_id",
          "type": "uuid",
          "primaryKey": false,
          "notNull": true
        },
        "name": {
          "name": "name",
          "type": "varchar(255)",
          "primaryKey": false,
          "notNull": true
        },
        "file_path": {
          "name": "file_path",
          "type": "varchar(500)",
          "primaryKey": false,
          "notNull": true
        },
        "file_size_original": {
          "name": "file_size_original",
          "type": "integer",
          "primaryKey": false,
          "notNull": true
        },
        "file_size_optimized": {
          "name": "file_size_optimized",
          "type": "integer",
          "primaryKey": false,
          "notNull": false
        },
        "svg_content": {
          "name": "svg_content",
          "type": "text",
          "primaryKey": false,
          "notNull": false
        },
        "status": {
          "name": "status",
          "type": "icon_status",
          "typeSchema": "public",
          "primaryKey": false,
          "notNull": true,
          "default": "'pending'"
        },
        "created_at": {
          "name": "created_at",
          "type": "timestamp with time zone",
          "primaryKey": false,
          "notNull": true,
          "default": "now()"
        },
        "updated_at": {
          "name": "updated_at",
          "type": "timestamp with time zone",
          "primaryKey": false,
          "notNull": true,
          "default": "now()"
        }
      },
      "indexes": {},
      "foreignKeys": {
        "icons_project_id_projects_id_fk": {
          "name": "icons_project_id_projects_id_fk",
          "tableFrom": "icons",
          "tableTo": "projects",
          "columnsFrom": [
            "project_id"
          ],
          "columnsTo": [
            "id"
          ],
          "onDelete": "cascade",
          "onUpdate": "no action"
        }
      },
      "compositePrimaryKeys": {},
      "uniqueConstraints": {
        "icons_project_id_name_unique": {
          "name": "icons_project_id_name_unique",
          "nullsNotDistinct": false,
          "columns": [
            "project_id",
            "name"
          ]
        }
      },
      "policies": {},
      "checkConstraints": {},
      "isRLSEnabled": false
    },
    "public.versions": {
      "name": "versions",
      "schema": "",
      "columns": {
        "id": {
          "name": "id",
          "type": "uuid",
          "primaryKey": true,
          "notNull": true,
          "default": "gen_random_uuid()"
        },
        "project_id": {
          "name": "project_id",
          "type": "uuid",
          "primaryKey": false,
          "notNull": true
        },
        "version": {
          "name": "version",
          "type": "varchar(50)",
          "primaryKey": false,
          "notNull": true
        },
        "type": {
          "name": "type",
          "type": "version_type",
          "typeSchema": "public",
          "primaryKey": false,
          "notNull": true
        },
        "changelog": {
          "name": "changelog",
          "type": "text",
          "primaryKey": false,
          "notNull": false
        },
        "icon_count": {
          "name": "icon_count",
          "type": "integer",
          "primaryKey": false,
          "notNull": true,
          "default": 0
        },
        "status": {
          "name": "status",
          "type": "version_status",
          "typeSchema": "public",
          "primaryKey": false,
          "notNull": true,
          "default": "'pending'"
        },
        "npm_url": {
          "name": "npm_url",
          "type": "varchar(500)",
          "primaryKey": false,
          "notNull": false
        },
        "build_log": {
          "name": "build_log",
          "type": "text",
          "primaryKey": false,
          "notNull": false
        },
        "published_at": {
          "name": "published_at",
          "type": "timestamp with time zone",
          "primaryKey": false,
          "notNull": false
        },
        "created_at": {
          "name": "created_at",
          "type": "timestamp with time zone",
          "primaryKey": false,
          "notNull": true,
          "default": "now()"
        },
        "updated_at": {
          "name": "updated_at",
          "type": "timestamp with time zone",
          "primaryKey": false,
          "notNull": true,
          "default": "now()"
        }
      },
      "indexes": {},
      "foreignKeys": {
        "versions_project_id_projects_id_fk": {
          "name": "versions_project_id_projects_id_fk",
          "tableFrom": "versions",
          "tableTo": "projects",
          "columnsFrom": [
            "project_id"
          ],
          "columnsTo": [
            "id"
          ],
          "onDelete": "cascade",
          "onUpdate": "no action"
        }
      },
      "compositePrimaryKeys": {},
      "uniqueConstraints": {
        "versions_project_id_version_unique": {
          "name": "versions_project_id_version_unique",
          "nullsNotDistinct": false,
          "columns": [
            "project_id",
            "version"
          ]
        }
      },
      "policies": {},
      "checkConstraints": {},
      "isRLSEnabled": false
    }
  },
  "enums": {
    "public.plan": {
      "name": "plan",
      "schema": "public",
      "values": [
        "free",
        "pro",
        "enterprise"
      ]
    },
    "public.project_status": {
      "name": "project_status",
      "schema": "public",
      "values": [
        "active",
        "archived"
      ]
    },
    "public.icon_status": {
      "name": "icon_status",
      "schema": "public",
      "values": [
        "pending",
        "optimized",
        "error"
      ]
    },
    "public.version_status": {
      "name": "version_status",
      "schema": "public",
      "values": [
        "pending",
        "building",
        "published",
        "failed"
      ]
    },
    "public.version_type": {
      "name": "version_type",
      "schema": "public",
      "values": [
        "major",
        "minor",
        "patch"
      ]
    }
  },
  "schemas": {},
  "sequences": {},
  "roles": {},
  "policies": {},
  "views": {},
  "_meta": {
    "columns": {},
    "schemas": {},
    "tables": {}
  }
}